{
  "data": [
    {
      "sourceCurrency": "JOD",
      "targetCurrency": "USD",
      "exChangeRateDate": "08/24/2025",
      "exChangeRateValue": 1.41036,
      "_service_date": "2025-08-24"
    },
    {
      "sourceCurrency": "JOD",
      "targetCurrency": "SAR",
      "exChangeRateDate": "08/24/2025",
      "exChangeRateValue": 5.29209,
      "_service_date": "2025-08-24"
    },
    {
      "sourceCurrency": "JOD",
      "targetCurrency": "EUR",
      "exChangeRateDate": "08/24/2025",
      "exChangeRateValue": 1.20318,
      "_service_date": "2025-08-24"
    },
    {
      "sourceCurrency": "JOD",
      "targetCurrency": "JPY",
      "exChangeRateDate": "08/24/2025",
      "exChangeRateValue": 207.26494,
      "_service_date": "2025-08-24"
    },
    {
      "sourceCurrency": "JOD",
      "targetCurrency": "AED",
      "exChangeRateDate": "08/24/2025",
      "exChangeRateValue": 5.17955,
      "_service_date": "2025-08-24"
    },
    {
      "sourceCurrency": "JOD",
      "targetCurrency": "GBP",
      "exChangeRateDate": "08/24/2025",
      "exChangeRateValue": 1.05113,
      "_service_date": "2025-08-24"
    },
    {
      "sourceCurrency": "JOD",
      "targetCurrency": "QAR",
      "exChangeRateDate": "08/24/2025",
      "exChangeRateValue": 5.08436,
      "_service_date": "2025-08-24"
    },
    {
      "sourceCurrency": "JOD",
      "targetCurrency": "CHF",
      "exChangeRateDate": "08/24/2025",
      "exChangeRateValue": 1.13974,
      "_service_date": "2025-08-24"
    },
    {
      "sourceCurrency": "JOD",
      "targetCurrency": "IQD",
      "exChangeRateDate": "08/24/2025",
      "exChangeRateValue": 1826.98843,
      "_service_date": "2025-08-24"
    },
    {
      "sourceCurrency": "USD",
      "targetCurrency": "JOD",
      "exChangeRateDate": "08/24/2025",
      "exChangeRateValue": 0.70904,
      "_service_date": "2025-08-24"
    },
    {
      "sourceCurrency": "USD",
      "targetCurrency": "SAR",
      "exChangeRateDate": "08/24/2025",
      "exChangeRateValue": 3.7523,
      "_service_date": "2025-08-24"
    },
    {
      "sourceCurrency": "USD",
      "targetCurrency": "EUR",
      "exChangeRateDate": "08/24/2025",
      "exChangeRateValue": 0.8531,
      "_service_date": "2025-08-24"
    },
    {
      "sourceCurrency": "USD",
      "targetCurrency": "AED",
      "exChangeRateDate": "08/24/2025",
      "exChangeRateValue": 3.6725,
      "_service_date": "2025-08-24"
    },
    {
      "sourceCurrency": "USD",
      "targetCurrency": "GBP",
      "exChangeRateDate": "08/24/2025",
      "exChangeRateValue": 0.7453,
      "_service_date": "2025-08-24"
    },
    {
      "sourceCurrency": "USD",
      "targetCurrency": "INR",
      "exChangeRateDate": "08/24/2025",
      "exChangeRateValue": 87.33025,
      "_service_date": "2025-08-24"
    },
    {
      "sourceCurrency": "USD",
      "targetCurrency": "EGP",
      "exChangeRateDate": "08/24/2025",
      "exChangeRateValue": 48.36198,
      "_service_date": "2025-08-24"
    },
    {
      "sourceCurrency": "USD",
      "targetCurrency": "QAR",
      "exChangeRateDate": "08/24/2025",
      "exChangeRateValue": 3.60502,
      "_service_date": "2025-08-24"
    },
    {
      "sourceCurrency": "USD",
      "targetCurrency": "ZAR",
      "exChangeRateDate": "08/24/2025",
      "exChangeRateValue": 17.4486,
      "_service_date": "2025-08-24"
    },
    {
      "sourceCurrency": "USD",
      "targetCurrency": "TRY",
      "exChangeRateDate": "08/24/2025",
      "exChangeRateValue": 40.93853,
      "_service_date": "2025-08-24"
    },
    {
      "sourceCurrency": "USD",
      "targetCurrency": "IQD",
      "exChangeRateDate": "08/24/2025",
      "exChangeRateValue": 1295.40705,
      "_service_date": "2025-08-24"
    },
    {
      "sourceCurrency": "SAR",
      "targetCurrency": "JOD",
      "exChangeRateDate": "08/24/2025",
      "exChangeRateValue": 0.18896,
      "_service_date": "2025-08-24"
    },
    {
      "sourceCurrency": "SAR",
      "targetCurrency": "USD",
      "exChangeRateDate": "08/24/2025",
      "exChangeRateValue": 0.2665,
      "_service_date": "2025-08-24"
    },
    {
      "sourceCurrency": "SAR",
      "targetCurrency": "EUR",
      "exChangeRateDate": "08/24/2025",
      "exChangeRateValue": 0.22736,
      "_service_date": "2025-08-24"
    },
    {
      "sourceCurrency": "SAR",
      "targetCurrency": "JPY",
      "exChangeRateDate": "08/24/2025",
      "exChangeRateValue": 39.16502,
      "_service_date": "2025-08-24"
    },
    {
      "sourceCurrency": "SAR",
      "targetCurrency": "AED",
      "exChangeRateDate": "08/24/2025",
      "exChangeRateValue": 0.97873,
      "_service_date": "2025-08-24"
    },
    {
      "sourceCurrency": "SAR",
      "targetCurrency": "AUD",
      "exChangeRateDate": "08/24/2025",
      "exChangeRateValue": 0.41203,
      "_service_date": "2025-08-24"
    },
    {
      "sourceCurrency": "SAR",
      "targetCurrency": "GBP",
      "exChangeRateDate": "08/24/2025",
      "exChangeRateValue": 0.19862,
      "_service_date": "2025-08-24"
    },
    {
      "sourceCurrency": "SAR",
      "targetCurrency": "INR",
      "exChangeRateDate": "08/24/2025",
      "exChangeRateValue": 23.27377,
      "_service_date": "2025-08-24"
    },
    {
      "sourceCurrency": "SAR",
      "targetCurrency": "EGP",
      "exChangeRateDate": "08/24/2025",
      "exChangeRateValue": 12.88861,
      "_service_date": "2025-08-24"
    },
    {
      "sourceCurrency": "SAR",
      "targetCurrency": "CAD",
      "exChangeRateDate": "08/24/2025",
      "exChangeRateValue": 0.36867,
      "_service_date": "2025-08-24"
    },
    {
      "sourceCurrency": "SAR",
      "targetCurrency": "QAR",
      "exChangeRateDate": "08/24/2025",
      "exChangeRateValue": 0.96075,
      "_service_date": "2025-08-24"
    },
    {
      "sourceCurrency": "SAR",
      "targetCurrency": "CHF",
      "exChangeRateDate": "08/24/2025",
      "exChangeRateValue": 0.21537,
      "_service_date": "2025-08-24"
    },
    {
      "sourceCurrency": "SAR",
      "targetCurrency": "SEK",
      "exChangeRateDate": "08/24/2025",
      "exChangeRateValue": 2.53001,
      "_service_date": "2025-08-24"
    },
    {
      "sourceCurrency": "SAR",
      "targetCurrency": "OMR",
      "exChangeRateDate": "08/24/2025",
      "exChangeRateValue": 0.10218,
      "_service_date": "2025-08-24"
    },
    {
      "sourceCurrency": "SAR",
      "targetCurrency": "KWD",
      "exChangeRateDate": "08/24/2025",
      "exChangeRateValue": 0.08139,
      "_service_date": "2025-08-24"
    },
    {
      "sourceCurrency": "SAR",
      "targetCurrency": "ZAR",
      "exChangeRateDate": "08/24/2025",
      "exChangeRateValue": 4.65011,
      "_service_date": "2025-08-24"
    },
    {
      "sourceCurrency": "SAR",
      "targetCurrency": "CNY",
      "exChangeRateDate": "08/24/2025",
      "exChangeRateValue": 1.91023,
      "_service_date": "2025-08-24"
    },
    {
      "sourceCurrency": "SAR",
      "targetCurrency": "TRY",
      "exChangeRateDate": "08/24/2025",
      "exChangeRateValue": 10.91024,
      "_service_date": "2025-08-24"
    },
    {
      "sourceCurrency": "SAR",
      "targetCurrency": "DKK",
      "exChangeRateDate": "08/24/2025",
      "exChangeRateValue": 1.69737,
      "_service_date": "2025-08-24"
    },
    {
      "sourceCurrency": "SAR",
      "targetCurrency": "thb",
      "exChangeRateDate": "08/24/2025",
      "exChangeRateValue": 8.63604,
      "_service_date": "2025-08-24"
    },
    {
      "sourceCurrency": "SAR",
      "targetCurrency": "NZD",
      "exChangeRateDate": "08/24/2025",
      "exChangeRateValue": 0.45428,
      "_service_date": "2025-08-24"
    },
    {
      "sourceCurrency": "SAR",
      "targetCurrency": "IQD",
      "exChangeRateDate": "08/24/2025",
      "exChangeRateValue": 345.22985,
      "_service_date": "2025-08-24"
    },
    {
      "sourceCurrency": "EUR",
      "targetCurrency": "JOD",
      "exChangeRateDate": "08/24/2025",
      "exChangeRateValue": 0.83113,
      "_service_date": "2025-08-24"
    },
    {
      "sourceCurrency": "EUR",
      "targetCurrency": "USD",
      "exChangeRateDate": "08/24/2025",
      "exChangeRateValue": 1.17219,
      "_service_date": "2025-08-24"
    },
    {
      "sourceCurrency": "EUR",
      "targetCurrency": "SAR",
      "exChangeRateDate": "08/24/2025",
      "exChangeRateValue": 4.39841,
      "_service_date": "2025-08-24"
    },
    {
      "sourceCurrency": "EUR",
      "targetCurrency": "AED",
      "exChangeRateDate": "08/24/2025",
      "exChangeRateValue": 4.30487,
      "_service_date": "2025-08-24"
    },
    {
      "sourceCurrency": "EUR",
      "targetCurrency": "GBP",
      "exChangeRateDate": "08/24/2025",
      "exChangeRateValue": 0.87363,
      "_service_date": "2025-08-24"
    },
    {
      "sourceCurrency": "EUR",
      "targetCurrency": "INR",
      "exChangeRateDate": "08/24/2025",
      "exChangeRateValue": 102.36764,
      "_service_date": "2025-08-24"
    },
    {
      "sourceCurrency": "EUR",
      "targetCurrency": "EGP",
      "exChangeRateDate": "08/24/2025",
      "exChangeRateValue": 56.68942,
      "_service_date": "2025-08-24"
    },
    {
      "sourceCurrency": "EUR",
      "targetCurrency": "QAR",
      "exChangeRateDate": "08/24/2025",
      "exChangeRateValue": 4.22576,
      "_service_date": "2025-08-24"
    },
    {
      "sourceCurrency": "EUR",
      "targetCurrency": "CHF",
      "exChangeRateDate": "08/24/2025",
      "exChangeRateValue": 0.94727,
      "_service_date": "2025-08-24"
    },
    {
      "sourceCurrency": "EUR",
      "targetCurrency": "ZAR",
      "exChangeRateDate": "08/24/2025",
      "exChangeRateValue": 20.45308,
      "_service_date": "2025-08-24"
    },
    {
      "sourceCurrency": "EUR",
      "targetCurrency": "TRY",
      "exChangeRateDate": "08/24/2025",
      "exChangeRateValue": 47.98773,
      "_service_date": "2025-08-24"
    },
    {
      "sourceCurrency": "EUR",
      "targetCurrency": "IQD",
      "exChangeRateDate": "08/24/2025",
      "exChangeRateValue": 1518.46305,
      "_service_date": "2025-08-24"
    },
    {
      "sourceCurrency": "JPY",
      "targetCurrency": "USD",
      "exChangeRateDate": "08/24/2025",
      "exChangeRateValue": 0.00681,
      "_service_date": "2025-08-24"
    },
    {
      "sourceCurrency": "JPY",
      "targetCurrency": "SAR",
      "exChangeRateDate": "08/24/2025",
      "exChangeRateValue": 0.02553,
      "_service_date": "2025-08-24"
    },
    {
      "sourceCurrency": "JPY",
      "targetCurrency": "EUR",
      "exChangeRateDate": "08/24/2025",
      "exChangeRateValue": 0.00581,
      "_service_date": "2025-08-24"
    },
    {
      "sourceCurrency": "JPY",
      "targetCurrency": "AED",
      "exChangeRateDate": "08/24/2025",
      "exChangeRateValue": 0.02499,
      "_service_date": "2025-08-24"
    },
    {
      "sourceCurrency": "JPY",
      "targetCurrency": "GBP",
      "exChangeRateDate": "08/24/2025",
      "exChangeRateValue": 0.00507,
      "_service_date": "2025-08-24"
    },
    {
      "sourceCurrency": "JPY",
      "targetCurrency": "EGP",
      "exChangeRateDate": "08/24/2025",
      "exChangeRateValue": 0.32909,
      "_service_date": "2025-08-24"
    },
    {
      "sourceCurrency": "JPY",
      "targetCurrency": "QAR",
      "exChangeRateDate": "08/24/2025",
      "exChangeRateValue": 0.02453,
      "_service_date": "2025-08-24"
    },
    {
      "sourceCurrency": "AED",
      "targetCurrency": "JOD",
      "exChangeRateDate": "08/24/2025",
      "exChangeRateValue": 0.19307,
      "_service_date": "2025-08-24"
    },
    {
      "sourceCurrency": "AED",
      "targetCurrency": "USD",
      "exChangeRateDate": "08/24/2025",
      "exChangeRateValue": 0.27229,
      "_service_date": "2025-08-24"
    },
    {
      "sourceCurrency": "AED",
      "targetCurrency": "SAR",
      "exChangeRateDate": "08/24/2025",
      "exChangeRateValue": 1.02173,
      "_service_date": "2025-08-24"
    },
    {
      "sourceCurrency": "AED",
      "targetCurrency": "EUR",
      "exChangeRateDate": "08/24/2025",
      "exChangeRateValue": 0.2323,
      "_service_date": "2025-08-24"
    },
    {
      "sourceCurrency": "AED",
      "targetCurrency": "JPY",
      "exChangeRateDate": "08/24/2025",
      "exChangeRateValue": 40.01603,
      "_service_date": "2025-08-24"
    },
    {
      "sourceCurrency": "AED",
      "targetCurrency": "AUD",
      "exChangeRateDate": "08/24/2025",
      "exChangeRateValue": 0.42099,
      "_service_date": "2025-08-24"
    },
    {
      "sourceCurrency": "AED",
      "targetCurrency": "GBP",
      "exChangeRateDate": "08/24/2025",
      "exChangeRateValue": 0.20294,
      "_service_date": "2025-08-24"
    },
    {
      "sourceCurrency": "AED",
      "targetCurrency": "INR",
      "exChangeRateDate": "08/24/2025",
      "exChangeRateValue": 23.77948,
      "_service_date": "2025-08-24"
    },
    {
      "sourceCurrency": "AED",
      "targetCurrency": "EGP",
      "exChangeRateDate": "08/24/2025",
      "exChangeRateValue": 13.16867,
      "_service_date": "2025-08-24"
    },
    {
      "sourceCurrency": "AED",
      "targetCurrency": "CAD",
      "exChangeRateDate": "08/24/2025",
      "exChangeRateValue": 0.37668,
      "_service_date": "2025-08-24"
    },
    {
      "sourceCurrency": "AED",
      "targetCurrency": "QAR",
      "exChangeRateDate": "08/24/2025",
      "exChangeRateValue": 0.98162,
      "_service_date": "2025-08-24"
    },
    {
      "sourceCurrency": "AED",
      "targetCurrency": "CHF",
      "exChangeRateDate": "08/24/2025",
      "exChangeRateValue": 0.22005,
      "_service_date": "2025-08-24"
    },
    {
      "sourceCurrency": "AED",
      "targetCurrency": "SEK",
      "exChangeRateDate": "08/24/2025",
      "exChangeRateValue": 2.58498,
      "_service_date": "2025-08-24"
    },
    {
      "sourceCurrency": "AED",
      "targetCurrency": "OMR",
      "exChangeRateDate": "08/24/2025",
      "exChangeRateValue": 0.1044,
      "_service_date": "2025-08-24"
    },
    {
      "sourceCurrency": "AED",
      "targetCurrency": "KWD",
      "exChangeRateDate": "08/24/2025",
      "exChangeRateValue": 0.08316,
      "_service_date": "2025-08-24"
    },
    {
      "sourceCurrency": "AED",
      "targetCurrency": "ZAR",
      "exChangeRateDate": "08/24/2025",
      "exChangeRateValue": 4.75115,
      "_service_date": "2025-08-24"
    },
    {
      "sourceCurrency": "AED",
      "targetCurrency": "CNY",
      "exChangeRateDate": "08/24/2025",
      "exChangeRateValue": 1.95173,
      "_service_date": "2025-08-24"
    },
    {
      "sourceCurrency": "AED",
      "targetCurrency": "TRY",
      "exChangeRateDate": "08/24/2025",
      "exChangeRateValue": 11.14731,
      "_service_date": "2025-08-24"
    },
    {
      "sourceCurrency": "AED",
      "targetCurrency": "DKK",
      "exChangeRateDate": "08/24/2025",
      "exChangeRateValue": 1.73425,
      "_service_date": "2025-08-24"
    },
    {
      "sourceCurrency": "AED",
      "targetCurrency": "thb",
      "exChangeRateDate": "08/24/2025",
      "exChangeRateValue": 8.82369,
      "_service_date": "2025-08-24"
    },
    {
      "sourceCurrency": "AED",
      "targetCurrency": "NZD",
      "exChangeRateDate": "08/24/2025",
      "exChangeRateValue": 0.46415,
      "_service_date": "2025-08-24"
    },
    {
      "sourceCurrency": "AED",
      "targetCurrency": "IQD",
      "exChangeRateDate": "08/24/2025",
      "exChangeRateValue": 352.73126,
      "_service_date": "2025-08-24"
    },
    {
      "sourceCurrency": "AUD",
      "targetCurrency": "USD",
      "exChangeRateDate": "08/24/2025",
      "exChangeRateValue": 0.6468,
      "_service_date": "2025-08-24"
    },
    {
      "sourceCurrency": "AUD",
      "targetCurrency": "SAR",
      "exChangeRateDate": "08/24/2025",
      "exChangeRateValue": 2.42699,
      "_service_date": "2025-08-24"
    },
    {
      "sourceCurrency": "AUD",
      "targetCurrency": "EUR",
      "exChangeRateDate": "08/24/2025",
      "exChangeRateValue": 0.55179,
      "_service_date": "2025-08-24"
    },
    {
      "sourceCurrency": "AUD",
      "targetCurrency": "AED",
      "exChangeRateDate": "08/24/2025",
      "exChangeRateValue": 2.37538,
      "_service_date": "2025-08-24"
    },
    {
      "sourceCurrency": "AUD",
      "targetCurrency": "GBP",
      "exChangeRateDate": "08/24/2025",
      "exChangeRateValue": 0.48206,
      "_service_date": "2025-08-24"
    },
    {
      "sourceCurrency": "AUD",
      "targetCurrency": "QAR",
      "exChangeRateDate": "08/24/2025",
      "exChangeRateValue": 2.33172,
      "_service_date": "2025-08-24"
    },
    {
      "sourceCurrency": "GBP",
      "targetCurrency": "JOD",
      "exChangeRateDate": "08/24/2025",
      "exChangeRateValue": 0.95135,
      "_service_date": "2025-08-24"
    },
    {
      "sourceCurrency": "GBP",
      "targetCurrency": "USD",
      "exChangeRateDate": "08/24/2025",
      "exChangeRateValue": 1.34175,
      "_service_date": "2025-08-24"
    },
    {
      "sourceCurrency": "GBP",
      "targetCurrency": "SAR",
      "exChangeRateDate": "08/24/2025",
      "exChangeRateValue": 5.03465,
      "_service_date": "2025-08-24"
    },
    {
      "sourceCurrency": "GBP",
      "targetCurrency": "EUR",
      "exChangeRateDate": "08/24/2025",
      "exChangeRateValue": 1.14465,
      "_service_date": "2025-08-24"
    },
    {
      "sourceCurrency": "GBP",
      "targetCurrency": "AED",
      "exChangeRateDate": "08/24/2025",
      "exChangeRateValue": 4.92758,
      "_service_date": "2025-08-24"
    },
    {
      "sourceCurrency": "GBP",
      "targetCurrency": "INR",
      "exChangeRateDate": "08/24/2025",
      "exChangeRateValue": 117.17536,
      "_service_date": "2025-08-24"
    },
    {
      "sourceCurrency": "GBP",
      "targetCurrency": "EGP",
      "exChangeRateDate": "08/24/2025",
      "exChangeRateValue": 64.88968,
      "_service_date": "2025-08-24"
    },
    {
      "sourceCurrency": "GBP",
      "targetCurrency": "QAR",
      "exChangeRateDate": "08/24/2025",
      "exChangeRateValue": 4.83703,
      "_service_date": "2025-08-24"
    },
    {
      "sourceCurrency": "GBP",
      "targetCurrency": "TRY",
      "exChangeRateDate": "08/24/2025",
      "exChangeRateValue": 54.92927,
      "_service_date": "2025-08-24"
    },
    {
      "sourceCurrency": "INR",
      "targetCurrency": "USD",
      "exChangeRateDate": "08/24/2025",
      "exChangeRateValue": 0.01145,
      "_service_date": "2025-08-24"
    },
    {
      "sourceCurrency": "INR",
      "targetCurrency": "SAR",
      "exChangeRateDate": "08/24/2025",
      "exChangeRateValue": 0.04297,
      "_service_date": "2025-08-24"
    },
    {
      "sourceCurrency": "INR",
      "targetCurrency": "EUR",
      "exChangeRateDate": "08/24/2025",
      "exChangeRateValue": 0.00977,
      "_service_date": "2025-08-24"
    },
    {
      "sourceCurrency": "INR",
      "targetCurrency": "AED",
      "exChangeRateDate": "08/24/2025",
      "exChangeRateValue": 0.04205,
      "_service_date": "2025-08-24"
    },
    {
      "sourceCurrency": "INR",
      "targetCurrency": "GBP",
      "exChangeRateDate": "08/24/2025",
      "exChangeRateValue": 0.00853,
      "_service_date": "2025-08-24"
    },
    {
      "sourceCurrency": "INR",
      "targetCurrency": "EGP",
      "exChangeRateDate": "08/24/2025",
      "exChangeRateValue": 0.55378,
      "_service_date": "2025-08-24"
    },
    {
      "sourceCurrency": "INR",
      "targetCurrency": "QAR",
      "exChangeRateDate": "08/24/2025",
      "exChangeRateValue": 0.04128,
      "_service_date": "2025-08-24"
    },
    {
      "sourceCurrency": "EGP",
      "targetCurrency": "USD",
      "exChangeRateDate": "08/24/2025",
      "exChangeRateValue": 0.02068,
      "_service_date": "2025-08-24"
    },
    {
      "sourceCurrency": "EGP",
      "targetCurrency": "SAR",
      "exChangeRateDate": "08/24/2025",
      "exChangeRateValue": 0.07759,
      "_service_date": "2025-08-24"
    },
    {
      "sourceCurrency": "EGP",
      "targetCurrency": "EUR",
      "exChangeRateDate": "08/24/2025",
      "exChangeRateValue": 0.01764,
      "_service_date": "2025-08-24"
    },
    {
      "sourceCurrency": "EGP",
      "targetCurrency": "AED",
      "exChangeRateDate": "08/24/2025",
      "exChangeRateValue": 0.07594,
      "_service_date": "2025-08-24"
    },
    {
      "sourceCurrency": "EGP",
      "targetCurrency": "GBP",
      "exChangeRateDate": "08/24/2025",
      "exChangeRateValue": 0.01541,
      "_service_date": "2025-08-24"
    },
    {
      "sourceCurrency": "EGP",
      "targetCurrency": "QAR",
      "exChangeRateDate": "08/24/2025",
      "exChangeRateValue": 0.07454,
      "_service_date": "2025-08-24"
    },
    {
      "sourceCurrency": "CAD",
      "targetCurrency": "USD",
      "exChangeRateDate": "08/24/2025",
      "exChangeRateValue": 0.72288,
      "_service_date": "2025-08-24"
    },
    {
      "sourceCurrency": "CAD",
      "targetCurrency": "SAR",
      "exChangeRateDate": "08/24/2025",
      "exChangeRateValue": 2.71248,
      "_service_date": "2025-08-24"
    },
    {
      "sourceCurrency": "CAD",
      "targetCurrency": "EUR",
      "exChangeRateDate": "08/24/2025",
      "exChangeRateValue": 0.61669,
      "_service_date": "2025-08-24"
    },
    {
      "sourceCurrency": "CAD",
      "targetCurrency": "AED",
      "exChangeRateDate": "08/24/2025",
      "exChangeRateValue": 2.65479,
      "_service_date": "2025-08-24"
    },
    {
      "sourceCurrency": "CAD",
      "targetCurrency": "GBP",
      "exChangeRateDate": "08/24/2025",
      "exChangeRateValue": 0.53876,
      "_service_date": "2025-08-24"
    },
    {
      "sourceCurrency": "CAD",
      "targetCurrency": "QAR",
      "exChangeRateDate": "08/24/2025",
      "exChangeRateValue": 2.606,
      "_service_date": "2025-08-24"
    },
    {
      "sourceCurrency": "QAR",
      "targetCurrency": "JOD",
      "exChangeRateDate": "08/24/2025",
      "exChangeRateValue": 0.19668,
      "_service_date": "2025-08-24"
    },
    {
      "sourceCurrency": "QAR",
      "targetCurrency": "SAR",
      "exChangeRateDate": "08/24/2025",
      "exChangeRateValue": 1.04086,
      "_service_date": "2025-08-24"
    },
    {
      "sourceCurrency": "QAR",
      "targetCurrency": "JPY",
      "exChangeRateDate": "08/24/2025",
      "exChangeRateValue": 40.76517,
      "_service_date": "2025-08-24"
    },
    {
      "sourceCurrency": "QAR",
      "targetCurrency": "AED",
      "exChangeRateDate": "08/24/2025",
      "exChangeRateValue": 1.01872,
      "_service_date": "2025-08-24"
    },
    {
      "sourceCurrency": "QAR",
      "targetCurrency": "AUD",
      "exChangeRateDate": "08/24/2025",
      "exChangeRateValue": 0.42887,
      "_service_date": "2025-08-24"
    },
    {
      "sourceCurrency": "QAR",
      "targetCurrency": "GBP",
      "exChangeRateDate": "08/24/2025",
      "exChangeRateValue": 0.20674,
      "_service_date": "2025-08-24"
    },
    {
      "sourceCurrency": "QAR",
      "targetCurrency": "INR",
      "exChangeRateDate": "08/24/2025",
      "exChangeRateValue": 24.22466,
      "_service_date": "2025-08-24"
    },
    {
      "sourceCurrency": "QAR",
      "targetCurrency": "EGP",
      "exChangeRateDate": "08/24/2025",
      "exChangeRateValue": 13.41519,
      "_service_date": "2025-08-24"
    },
    {
      "sourceCurrency": "QAR",
      "targetCurrency": "CAD",
      "exChangeRateDate": "08/24/2025",
      "exChangeRateValue": 0.38373,
      "_service_date": "2025-08-24"
    },
    {
      "sourceCurrency": "QAR",
      "targetCurrency": "CHF",
      "exChangeRateDate": "08/24/2025",
      "exChangeRateValue": 0.22417,
      "_service_date": "2025-08-24"
    },
    {
      "sourceCurrency": "QAR",
      "targetCurrency": "SEK",
      "exChangeRateDate": "08/24/2025",
      "exChangeRateValue": 2.63337,
      "_service_date": "2025-08-24"
    },
    {
      "sourceCurrency": "QAR",
      "targetCurrency": "OMR",
      "exChangeRateDate": "08/24/2025",
      "exChangeRateValue": 0.10635,
      "_service_date": "2025-08-24"
    },
    {
      "sourceCurrency": "QAR",
      "targetCurrency": "KWD",
      "exChangeRateDate": "08/24/2025",
      "exChangeRateValue": 0.08471,
      "_service_date": "2025-08-24"
    },
    {
      "sourceCurrency": "QAR",
      "targetCurrency": "ZAR",
      "exChangeRateDate": "08/24/2025",
      "exChangeRateValue": 4.84009,
      "_service_date": "2025-08-24"
    },
    {
      "sourceCurrency": "QAR",
      "targetCurrency": "CNY",
      "exChangeRateDate": "08/24/2025",
      "exChangeRateValue": 1.98827,
      "_service_date": "2025-08-24"
    },
    {
      "sourceCurrency": "QAR",
      "targetCurrency": "TRY",
      "exChangeRateDate": "08/24/2025",
      "exChangeRateValue": 11.35599,
      "_service_date": "2025-08-24"
    },
    {
      "sourceCurrency": "QAR",
      "targetCurrency": "DKK",
      "exChangeRateDate": "08/24/2025",
      "exChangeRateValue": 1.76672,
      "_service_date": "2025-08-24"
    },
    {
      "sourceCurrency": "QAR",
      "targetCurrency": "thb",
      "exChangeRateDate": "08/24/2025",
      "exChangeRateValue": 8.98888,
      "_service_date": "2025-08-24"
    },
    {
      "sourceCurrency": "QAR",
      "targetCurrency": "NZD",
      "exChangeRateDate": "08/24/2025",
      "exChangeRateValue": 0.47284,
      "_service_date": "2025-08-24"
    },
    {
      "sourceCurrency": "CHF",
      "targetCurrency": "USD",
      "exChangeRateDate": "08/24/2025",
      "exChangeRateValue": 1.23743,
      "_service_date": "2025-08-24"
    },
    {
      "sourceCurrency": "CHF",
      "targetCurrency": "SAR",
      "exChangeRateDate": "08/24/2025",
      "exChangeRateValue": 4.64323,
      "_service_date": "2025-08-24"
    },
    {
      "sourceCurrency": "CHF",
      "targetCurrency": "EUR",
      "exChangeRateDate": "08/24/2025",
      "exChangeRateValue": 1.05566,
      "_service_date": "2025-08-24"
    },
    {
      "sourceCurrency": "CHF",
      "targetCurrency": "AED",
      "exChangeRateDate": "08/24/2025",
      "exChangeRateValue": 4.54448,
      "_service_date": "2025-08-24"
    },
    {
      "sourceCurrency": "CHF",
      "targetCurrency": "GBP",
      "exChangeRateDate": "08/24/2025",
      "exChangeRateValue": 0.92225,
      "_service_date": "2025-08-24"
    },
    {
      "sourceCurrency": "CHF",
      "targetCurrency": "QAR",
      "exChangeRateDate": "08/24/2025",
      "exChangeRateValue": 4.46097,
      "_service_date": "2025-08-24"
    },
    {
      "sourceCurrency": "SEK",
      "targetCurrency": "SAR",
      "exChangeRateDate": "08/24/2025",
      "exChangeRateValue": 0.39526,
      "_service_date": "2025-08-24"
    },
    {
      "sourceCurrency": "OMR",
      "targetCurrency": "SAR",
      "exChangeRateDate": "08/24/2025",
      "exChangeRateValue": 9.78686,
      "_service_date": "2025-08-24"
    },
    {
      "sourceCurrency": "OMR",
      "targetCurrency": "AED",
      "exChangeRateDate": "08/24/2025",
      "exChangeRateValue": 9.57872,
      "_service_date": "2025-08-24"
    },
    {
      "sourceCurrency": "OMR",
      "targetCurrency": "QAR",
      "exChangeRateDate": "08/24/2025",
      "exChangeRateValue": 9.4027,
      "_service_date": "2025-08-24"
    },
    {
      "sourceCurrency": "KWD",
      "targetCurrency": "SAR",
      "exChangeRateDate": "08/24/2025",
      "exChangeRateValue": 12.28691,
      "_service_date": "2025-08-24"
    },
    {
      "sourceCurrency": "KWD",
      "targetCurrency": "EUR",
      "exChangeRateDate": "08/24/2025",
      "exChangeRateValue": 2.79349,
      "_service_date": "2025-08-24"
    },
    {
      "sourceCurrency": "KWD",
      "targetCurrency": "AED",
      "exChangeRateDate": "08/24/2025",
      "exChangeRateValue": 12.0256,
      "_service_date": "2025-08-24"
    },
    {
      "sourceCurrency": "KWD",
      "targetCurrency": "GBP",
      "exChangeRateDate": "08/24/2025",
      "exChangeRateValue": 2.44047,
      "_service_date": "2025-08-24"
    },
    {
      "sourceCurrency": "KWD",
      "targetCurrency": "QAR",
      "exChangeRateDate": "08/24/2025",
      "exChangeRateValue": 11.80461,
      "_service_date": "2025-08-24"
    },
    {
      "sourceCurrency": "ZAR",
      "targetCurrency": "USD",
      "exChangeRateDate": "08/24/2025",
      "exChangeRateValue": 0.05731,
      "_service_date": "2025-08-24"
    },
    {
      "sourceCurrency": "ZAR",
      "targetCurrency": "SAR",
      "exChangeRateDate": "08/24/2025",
      "exChangeRateValue": 0.21505,
      "_service_date": "2025-08-24"
    },
    {
      "sourceCurrency": "ZAR",
      "targetCurrency": "AED",
      "exChangeRateDate": "08/24/2025",
      "exChangeRateValue": 0.21048,
      "_service_date": "2025-08-24"
    },
    {
      "sourceCurrency": "ZAR",
      "targetCurrency": "EGP",
      "exChangeRateDate": "08/24/2025",
      "exChangeRateValue": 2.77168,
      "_service_date": "2025-08-24"
    },
    {
      "sourceCurrency": "ZAR",
      "targetCurrency": "QAR",
      "exChangeRateDate": "08/24/2025",
      "exChangeRateValue": 0.20661,
      "_service_date": "2025-08-24"
    },
    {
      "sourceCurrency": "CNY",
      "targetCurrency": "USD",
      "exChangeRateDate": "08/24/2025",
      "exChangeRateValue": 0.13951,
      "_service_date": "2025-08-24"
    },
    {
      "sourceCurrency": "CNY",
      "targetCurrency": "SAR",
      "exChangeRateDate": "08/24/2025",
      "exChangeRateValue": 0.5235,
      "_service_date": "2025-08-24"
    },
    {
      "sourceCurrency": "CNY",
      "targetCurrency": "EUR",
      "exChangeRateDate": "08/24/2025",
      "exChangeRateValue": 0.11902,
      "_service_date": "2025-08-24"
    },
    {
      "sourceCurrency": "CNY",
      "targetCurrency": "AED",
      "exChangeRateDate": "08/24/2025",
      "exChangeRateValue": 0.51237,
      "_service_date": "2025-08-24"
    },
    {
      "sourceCurrency": "CNY",
      "targetCurrency": "GBP",
      "exChangeRateDate": "08/24/2025",
      "exChangeRateValue": 0.10398,
      "_service_date": "2025-08-24"
    },
    {
      "sourceCurrency": "CNY",
      "targetCurrency": "QAR",
      "exChangeRateDate": "08/24/2025",
      "exChangeRateValue": 0.50295,
      "_service_date": "2025-08-24"
    },
    {
      "sourceCurrency": "NZD",
      "targetCurrency": "USD",
      "exChangeRateDate": "08/24/2025",
      "exChangeRateValue": 0.58665,
      "_service_date": "2025-08-24"
    },
    {
      "sourceCurrency": "NZD",
      "targetCurrency": "SAR",
      "exChangeRateDate": "08/24/2025",
      "exChangeRateValue": 2.20127,
      "_service_date": "2025-08-24"
    },
    {
      "sourceCurrency": "NZD",
      "targetCurrency": "AED",
      "exChangeRateDate": "08/24/2025",
      "exChangeRateValue": 2.15446,
      "_service_date": "2025-08-24"
    },
    {
      "sourceCurrency": "NZD",
      "targetCurrency": "QAR",
      "exChangeRateDate": "08/24/2025",
      "exChangeRateValue": 2.11486,
      "_service_date": "2025-08-24"
    },
    {
      "sourceCurrency": "KRW",
      "targetCurrency": "USD",
      "exChangeRateDate": "08/24/2025",
      "exChangeRateValue": 0.00072,
      "_service_date": "2025-08-24"
    },
    {
      "sourceCurrency": "KRW",
      "targetCurrency": "SAR",
      "exChangeRateDate": "08/24/2025",
      "exChangeRateValue": 0.00271,
      "_service_date": "2025-08-24"
    },
    {
      "sourceCurrency": "KRW",
      "targetCurrency": "EUR",
      "exChangeRateDate": "08/24/2025",
      "exChangeRateValue": 0.00062,
      "_service_date": "2025-08-24"
    },
    {
      "sourceCurrency": "KRW",
      "targetCurrency": "GBP",
      "exChangeRateDate": "08/24/2025",
      "exChangeRateValue": 0.00054,
      "_service_date": "2025-08-24"
    },
    {
      "sourceCurrency": "KRW",
      "targetCurrency": "QAR",
      "exChangeRateDate": "08/24/2025",
      "exChangeRateValue": 0.0026,
      "_service_date": "2025-08-24"
    },
    {
      "sourceCurrency": "NOK",
      "targetCurrency": "USD",
      "exChangeRateDate": "08/24/2025",
      "exChangeRateValue": 0.09944,
      "_service_date": "2025-08-24"
    },
    {
      "sourceCurrency": "NOK",
      "targetCurrency": "SAR",
      "exChangeRateDate": "08/24/2025",
      "exChangeRateValue": 0.37312,
      "_service_date": "2025-08-24"
    },
    {
      "sourceCurrency": "NOK",
      "targetCurrency": "EUR",
      "exChangeRateDate": "08/24/2025",
      "exChangeRateValue": 0.08483,
      "_service_date": "2025-08-24"
    },
    {
      "sourceCurrency": "NOK",
      "targetCurrency": "GBP",
      "exChangeRateDate": "08/24/2025",
      "exChangeRateValue": 0.07411,
      "_service_date": "2025-08-24"
    },
    {
      "sourceCurrency": "NOK",
      "targetCurrency": "QAR",
      "exChangeRateDate": "08/24/2025",
      "exChangeRateValue": 0.35847,
      "_service_date": "2025-08-24"
    },
    {
      "sourceCurrency": "TRY",
      "targetCurrency": "USD",
      "exChangeRateDate": "08/24/2025",
      "exChangeRateValue": 0.02443,
      "_service_date": "2025-08-24"
    },
    {
      "sourceCurrency": "TRY",
      "targetCurrency": "SAR",
      "exChangeRateDate": "08/24/2025",
      "exChangeRateValue": 0.09166,
      "_service_date": "2025-08-24"
    },
    {
      "sourceCurrency": "TRY",
      "targetCurrency": "EUR",
      "exChangeRateDate": "08/24/2025",
      "exChangeRateValue": 0.02084,
      "_service_date": "2025-08-24"
    },
    {
      "sourceCurrency": "TRY",
      "targetCurrency": "AED",
      "exChangeRateDate": "08/24/2025",
      "exChangeRateValue": 0.08971,
      "_service_date": "2025-08-24"
    },
    {
      "sourceCurrency": "TRY",
      "targetCurrency": "GBP",
      "exChangeRateDate": "08/24/2025",
      "exChangeRateValue": 0.01821,
      "_service_date": "2025-08-24"
    },
    {
      "sourceCurrency": "TRY",
      "targetCurrency": "QAR",
      "exChangeRateDate": "08/24/2025",
      "exChangeRateValue": 0.08806,
      "_service_date": "2025-08-24"
    },
    {
      "sourceCurrency": "TRY",
      "targetCurrency": "ZAR",
      "exChangeRateDate": "08/24/2025",
      "exChangeRateValue": 0.42622,
      "_service_date": "2025-08-24"
    },
    {
      "sourceCurrency": "DKK",
      "targetCurrency": "USD",
      "exChangeRateDate": "08/24/2025",
      "exChangeRateValue": 0.15701,
      "_service_date": "2025-08-24"
    },
    {
      "sourceCurrency": "DKK",
      "targetCurrency": "SAR",
      "exChangeRateDate": "08/24/2025",
      "exChangeRateValue": 0.58915,
      "_service_date": "2025-08-24"
    },
    {
      "sourceCurrency": "DKK",
      "targetCurrency": "EUR",
      "exChangeRateDate": "08/24/2025",
      "exChangeRateValue": 0.13395,
      "_service_date": "2025-08-24"
    },
    {
      "sourceCurrency": "DKK",
      "targetCurrency": "AED",
      "exChangeRateDate": "08/24/2025",
      "exChangeRateValue": 0.57662,
      "_service_date": "2025-08-24"
    },
    {
      "sourceCurrency": "DKK",
      "targetCurrency": "GBP",
      "exChangeRateDate": "08/24/2025",
      "exChangeRateValue": 0.11702,
      "_service_date": "2025-08-24"
    },
    {
      "sourceCurrency": "DKK",
      "targetCurrency": "QAR",
      "exChangeRateDate": "08/24/2025",
      "exChangeRateValue": 0.56602,
      "_service_date": "2025-08-24"
    },
    {
      "sourceCurrency": "THB",
      "targetCurrency": "USD",
      "exChangeRateDate": "08/24/2025",
      "exChangeRateValue": 0.03086,
      "_service_date": "2025-08-24"
    },
    {
      "sourceCurrency": "THB",
      "targetCurrency": "SAR",
      "exChangeRateDate": "08/24/2025",
      "exChangeRateValue": 0.11579,
      "_service_date": "2025-08-24"
    },
    {
      "sourceCurrency": "THB",
      "targetCurrency": "AED",
      "exChangeRateDate": "08/24/2025",
      "exChangeRateValue": 0.11333,
      "_service_date": "2025-08-24"
    },
    {
      "sourceCurrency": "THB",
      "targetCurrency": "QAR",
      "exChangeRateDate": "08/24/2025",
      "exChangeRateValue": 0.11125,
      "_service_date": "2025-08-24"
    },
    {
      "sourceCurrency": "THB",
      "targetCurrency": "TRY",
      "exChangeRateDate": "08/24/2025",
      "exChangeRateValue": 1.26334,
      "_service_date": "2025-08-24"
    },
    {
      "sourceCurrency": "IQD",
      "targetCurrency": "JOD",
      "exChangeRateDate": "08/24/2025",
      "exChangeRateValue": 0.00055,
      "_service_date": "2025-08-24"
    },
    {
      "sourceCurrency": "IQD",
      "targetCurrency": "USD",
      "exChangeRateDate": "08/24/2025",
      "exChangeRateValue": 0.00077,
      "_service_date": "2025-08-24"
    },
    {
      "sourceCurrency": "IQD",
      "targetCurrency": "SAR",
      "exChangeRateDate": "08/24/2025",
      "exChangeRateValue": 0.0029,
      "_service_date": "2025-08-24"
    },
    {
      "sourceCurrency": "IQD",
      "targetCurrency": "EUR",
      "exChangeRateDate": "08/24/2025",
      "exChangeRateValue": 0.00066,
      "_service_date": "2025-08-24"
    },
    {
      "sourceCurrency": "IQD",
      "targetCurrency": "AED",
      "exChangeRateDate": "08/24/2025",
      "exChangeRateValue": 0.00284,
      "_service_date": "2025-08-24"
    }
  ]
}